dinosay/__init__.py
dinosay/dinosay.py
dinosay-1.2.0.dist-info/LICENSE.md
dinosay-1.2.0.dist-info/METADATA
dinosay-1.2.0.dist-info/WHEEL
dinosay-1.2.0.dist-info/entry_points.txt
dinosay-1.2.0.dist-info/top_level.txt
dinosay-1.2.0.dist-info/RECORD
