Metadata-Version: 2.1
Name: dinosay
Version: 1.2.0
Summary: dinosay is a humble, simple, nice and paleolithic alternative to cowsay
Home-page: https://github.com/MatteoGuadrini/dinosay
Author: Matteo Guadrini
Author-email: matteo.guadrini@hotmail.it
Maintainer: Matteo Guadrini
Maintainer-email: matteo.guadrini@hotmail.it
License: GNU General Public License v3.0
Project-URL: Documentation, https://matteoguadrini.github.io/dinosay
Project-URL: GitHub Project, https://github.com/MatteoGuadrini/dinosay
Project-URL: Issue Tracker, https://github.com/MatteoGuadrini/dinosay/issues
Platform: UNKNOWN
Classifier: Programming Language :: Python :: 3
Classifier: License :: OSI Approved :: GNU General Public License v3 (GPLv3)
Classifier: Operating System :: OS Independent
Requires-Python: >=3.5
License-File: LICENSE.md
